[{"data": {"accommodationType": [], "restaurantStyles": [{"tag": {"categoryId": 235, "tagId": 10604, "tagName": "Families with children", "tagNameLocalized": "Gia \u0111i\u0300nh co\u0301 tre\u0309 em", "translationKey": "tags_category_tag_families_with_children"}}, {"tag": {"categoryId": 235, "tagId": 10608, "tagName": "Bar scene", "tagNameLocalized": "Quang ca\u0309nh qu\u00e2\u0300y bar", "translationKey": "tags_category_tag_bar_scene"}}, {"tag": {"categoryId": 235, "tagId": 10609, "tagName": "Large groups", "tagNameLocalized": "Nho\u0301m l\u01a1\u0301n", "translationKey": "tags_category_tag_large_groups"}}, {"tag": {"categoryId": 235, "tagId": 11777, "tagName": "Kids", "tagNameLocalized": "Tr\u1ebb em", "translationKey": "tags_category_tag_kids"}}], "restaurantTypes": [{"tag": {"categoryId": 230, "tagId": 10591, "tagName": "Restaurants", "tagNameLocalized": "Nha\u0300 ha\u0300ng", "translationKey": "tags_category_tag_restaurants"}}], "restaurantMealTypes": [{"tag": {"categoryId": 233, "tagId": 10598, "tagName": "Lunch", "tagNameLocalized": "B\u01b0\u0303a tr\u01b0a", "translationKey": "tags_category_tag_lunch"}}, {"tag": {"categoryId": 233, "tagId": 10599, "tagName": "Dinner", "tagNameLocalized": "B\u01b0\u0303a t\u00f4\u0301i", "translationKey": "tags_category_tag_dinner"}}], "restaurantDiningOptions": [{"tag": {"categoryId": 234, "tagId": 10601, "tagName": "Takeout", "tagNameLocalized": "C\u01b0\u0309a ha\u0300ng ba\u0301n th\u01b0\u0301c \u0103n mang v\u00ea\u0300", "translationKey": "tags_category_tag_takeout"}}, {"tag": {"categoryId": 234, "tagId": 10859, "tagName": "Television", "tagNameLocalized": "Tivi", "translationKey": "tags_category_tag_television"}}, {"tag": {"categoryId": 234, "tagId": 16547, "tagName": "Table Service", "tagNameLocalized": "D\u1ecbch v\u1ee5 b\u00e0n", "translationKey": "tags_category_tag_table_service"}}, {"tag": {"categoryId": 234, "tagId": 10862, "tagName": "Serves Alcohol", "tagNameLocalized": "Ph\u1ee5c v\u1ee5 \u0111\u1ed3 u\u1ed1ng c\u00f3 c\u1ed3n", "translationKey": "tags_category_tag_serves_alcohol"}}, {"tag": {"categoryId": 234, "tagId": 10861, "tagName": "Wheelchair Accessible", "tagNameLocalized": "L\u1ed1i v\u00e0o ra cho xe l\u0103n", "translationKey": "tags_category_tag_wheelchair_accessible"}}, {"tag": {"categoryId": 234, "tagId": 10852, "tagName": "Seating", "tagNameLocalized": "Ch\u1ed7 ng\u1ed3i", "translationKey": "tags_category_tag_seating"}}, {"tag": {"categoryId": 234, "tagId": 10863, "tagName": "Full Bar", "tagNameLocalized": "Qu\u00e2\u0300y bar \u0111\u00e2\u0300y \u0111u\u0309", "translationKey": "tags_category_tag_full_bar"}}], "restaurantPrice": [{"tag": {"categoryId": 240, "tagId": 10955, "tagName": "Mid Range", "tagNameLocalized": "H\u1ea1ng trung", "translationKey": "tags_category_tag_mid_range"}}], "restaurantCuisines": [{"tag": {"categoryId": 231, "tagId": 10634, "tagName": "Southwestern", "tagNameLocalized": "Ki\u00ea\u0309u T\u00e2y nam", "translationKey": "tags_category_tag_southwestern"}}, {"tag": {"categoryId": 231, "tagId": 9908, "tagName": "American", "tagNameLocalized": "Ki\u1ec3u My\u0303", "translationKey": "tags_category_tag_american"}}, {"tag": {"categoryId": 231, "tagId": 10640, "tagName": "Bar", "tagNameLocalized": "Qu\u00e2\u0300y bar", "translationKey": "tags_category_tag_bar"}}], "locations": [{"accommodationType": "T_UNKNOWN", "countryId": 191, "hoursOfOperation": {"dailyTimeIntervals": [{"day": "MONDAY", "timeIntervals": [{"openingTime": {"hours": 11, "minutes": 0}, "closingTime": {"hours": 22, "minutes": 0}}]}, {"day": "TUESDAY", "timeIntervals": [{"openingTime": {"hours": 11, "minutes": 0}, "closingTime": {"hours": 22, "minutes": 0}}]}, {"day": "WEDNESDAY", "timeIntervals": [{"openingTime": {"hours": 11, "minutes": 0}, "closingTime": {"hours": 22, "minutes": 0}}]}, {"day": "THURSDAY", "timeIntervals": [{"openingTime": {"hours": 11, "minutes": 0}, "closingTime": {"hours": 22, "minutes": 0}}]}, {"day": "FRIDAY", "timeIntervals": [{"openingTime": {"hours": 11, "minutes": 0}, "closingTime": {"hours": 23, "minutes": 0}}]}, {"day": "SATURDAY", "timeIntervals": [{"openingTime": {"hours": 11, "minutes": 0}, "closingTime": {"hours": 23, "minutes": 0}}]}, {"day": "SUNDAY", "timeIntervals": [{"openingTime": {"hours": 11, "minutes": 0}, "closingTime": {"hours": 22, "minutes": 0}}]}]}, "isClosed": false, "isOwner": false, "latitude": 39.953083, "localizedDescriptions": [], "localizedNames": [], "locationId": 478484, "locationV2": {"attractionTypes": []}, "longitude": -75.161026, "parentId": 60795, "placeType": "EATERY", "absoluteOwnerManagementUrl": "https://www.tripadvisor.com.vn/RSManagementCenter-d478484-Chili_s_Grill_Bar?cat=0&geo=60795", "email": "", "geoName": "Philadelphia", "isoCountryCode": "US", "localizedName": "Chili's Grill & Bar", "name": "Chili's Grill & Bar", "locationDescription": null, "officialUrl": "http://www.chilis.com/locations/us/pennsylvania/philadelphia/center-city", "postPhotosUrl": "/PostPhotos-d478484", "telephone": "+1 215-569-0850", "url": "/Restaurant_Review-g60795-d478484-Reviews-Chili_s_Grill_Bar-Philadelphia_Pennsylvania.html", "writeUserReviewUrl": "/UserReview-g60795-d478484-Chili_s_Grill_Bar-Philadelphia_Pennsylvania.html", "localizedStreetAddress": {"city": "Philadelphia", "country": "Hoa K\u1ef3", "fullAddress": "1239 Filbert St, Philadelphia, PA 19107", "postalCode": "19107", "state": "Pennsylvania:", "street1": "1239 Filbert St", "street2": ""}, "streetAddress": {"street1": "1239 Filbert St", "street2": "", "state": "Pennsylvania:", "city": "Philadelphia", "postalCode": "19107", "fullAddress": "1239 Filbert St, Philadelphia, PA 19107"}, "localizedStreetAddresses": [{"street1": null, "street2": null, "fullAddress": "1239 Filbert St, Philadelphie, PA 19107", "locale": "fr_BE"}, {"street1": null, "street2": null, "fullAddress": "1239 Filbert St, Filadelfia, PA 19107", "locale": "es_MX"}, {"street1": null, "street2": null, "fullAddress": "1239 Filbert St, Filadelfia, PA 19107", "locale": "es_VE"}, {"street1": null, "street2": null, "fullAddress": "1239 Filbert St, \u8cbb\u57ce, PA", "locale": "zh_TW"}, {"street1": null, "street2": null, "fullAddress": "1239 Filbert St, \u8cbb\u57ce, PA", "locale": "zh_HK"}, {"street1": null, "street2": null, "fullAddress": "1239 Filbert St, Philadelphia, PA 19107", "locale": "it"}, {"street1": null, "street2": null, "fullAddress": "1239 Filbert St, \ud544\ub77c\ub378\ud53c\uc544, PA", "locale": "ko"}, {"street1": null, "street2": null, "fullAddress": "1239 Filbert St, Filadelfia, PA 19107", "locale": "es_CL"}, {"street1": null, "street2": null, "fullAddress": "1239 Filbert St, Philadelphia, PA 19107", "locale": "fi"}, {"street1": null, "street2": null, "fullAddress": "1239 Filbert St, Filad\u00e9lfia, PA 19107", "locale": "pt_PT"}, {"street1": null, "street2": null, "fullAddress": "1239 Filbert St, Philadelphia, PA 19107", "locale": "en_US"}, {"street1": null, "street2": null, "fullAddress": "1239 Filbert St, \u0e1f\u0e34\u0e25\u0e32\u0e40\u0e14\u0e25\u0e40\u0e1f\u0e35\u0e22, PA 19107", "locale": "th"}, {"street1": null, "street2": null, "fullAddress": "1239 Filbert St, Philadelphia, PA 19107", "locale": "en_SG"}, {"street1": null, "street2": null, "fullAddress": "1239 Filbert St, Philadelphia, PA 19107", "locale": "en_UK"}, {"street1": null, "street2": null, "fullAddress": "1239 Filbert St, Filad\u00e9lfia, PA 19107", "locale": "pt"}, {"street1": null, "street2": null, "fullAddress": "1239 Filbert St, \u0641\u064a\u0644\u0627\u062f\u0644\u0641\u064a\u0627, \u0628\u0646\u0633\u064a\u0644\u0641\u0627\u0646\u064a\u0627 19107", "locale": "ar"}, {"street1": null, "street2": null, "fullAddress": "1239 Filbert St, \u0424\u0438\u043b\u0430\u0434\u0435\u043b\u044c\u0444\u0438\u044f, PA 19107", "locale": "ru"}, {"street1": null, "street2": null, "fullAddress": "1239 Filbert St, Philadelphia, PA 19107", "locale": "en_NZ"}, {"street1": null, "street2": null, "fullAddress": "1239 Filbert St, Philadelphia, PA 19107", "locale": "de_CH"}, {"street1": null, "street2": null, "fullAddress": "1239 Filbert St, Philadelphia, PA 19107", "locale": "sk"}, {"street1": null, "street2": null, "fullAddress": "1239 Filbert St, Philadelphia, PA 19107", "locale": "en_ZA"}, {"street1": null, "street2": null, "fullAddress": "1239 Filbert St, Filadelfie, PA 19107", "locale": "cs"}, {"street1": null, "street2": null, "fullAddress": "1239 Filbert St, Philadelphia, PA 19107", "locale": "sv"}, {"street1": null, "street2": null, "fullAddress": "1239 Filbert St, \u03a6\u03b9\u03bb\u03b1\u03b4\u03ad\u03bb\u03c6\u03b5\u03b9\u03b1, PA 19107", "locale": "el"}, {"street1": null, "street2": null, "fullAddress": "1239 Filbert St, Philadelphia, PA 19107", "locale": "de_AT"}, {"street1": null, "street2": null, "fullAddress": "1239 Filbert St, Philadelphia, PA 19107", "locale": "hu"}, {"street1": null, "street2": null, "fullAddress": "1239 Filbert St, Philadelphie, PA 19107", "locale": "fr_CH"}, {"street1": null, "street2": null, "fullAddress": "1239 Filbert St, Philadelphia, PA 19107", "locale": "nl"}, {"street1": null, "street2": null, "fullAddress": "1239 Filbert St, Philadelphia, PA 19107", "locale": "en_AU"}, {"street1": null, "street2": null, "fullAddress": "1239 Filbert St, Philadelphia, PA 19107", "locale": "in"}, {"street1": null, "street2": null, "fullAddress": "1239 Filbert St, Philadelphia, PA 19107", "locale": "vi"}, {"street1": null, "street2": null, "fullAddress": "1239 Filbert St, Philadelphie, PA 19107", "locale": "fr_CA"}, {"street1": null, "street2": null, "fullAddress": "1239 Filbert St, Filadelfia, PA 19107", "locale": "es_AR"}, {"street1": null, "street2": null, "fullAddress": "1239 Filbert St, \u0641\u064a\u0644\u0627\u062f\u0644\u0641\u064a\u0627, \u0628\u0646\u0633\u064a\u0644\u0641\u0627\u0646\u064a\u0627 19107", "locale": "ar_EG"}, {"street1": null, "street2": null, "fullAddress": "1239 Filbert St, Filadelfija, PA 19107", "locale": "sr"}, {"street1": null, "street2": null, "fullAddress": "1239 Filbert St, Philadelphia, PA 19107", "locale": "en_MY"}, {"street1": null, "street2": null, "fullAddress": "1239 Filbert St, Philadelphia, PA 19107", "locale": "it_CH"}, {"street1": null, "street2": null, "fullAddress": "1239 Filbert St, Philadelphia, PA 19107", "locale": "da"}, {"street1": null, "street2": null, "fullAddress": "1239 Filbert St, Filadelfia, PA 19107", "locale": "es"}, {"street1": null, "street2": null, "fullAddress": "1239 Filbert St, Philadelphia, PA 19107", "locale": "tr"}, {"street1": null, "street2": null, "fullAddress": "1239 Filbert St, Philadelphia, PA 19107", "locale": "en_HK"}, {"street1": null, "street2": null, "fullAddress": "1239 Filbert St, Philadelphia, PA 19107", "locale": "en_IE"}, {"street1": null, "street2": null, "fullAddress": "1239 Filbert St, Philadelphia, PA 19107", "locale": "en_CA"}, {"street1": null, "street2": null, "fullAddress": "1239 Filbert St, Philadelphia, PA 19107", "locale": "no"}, {"street1": null, "street2": null, "fullAddress": "1239 Filbert St, Philadelphia, PA 19107", "locale": "nl_BE"}, {"street1": null, "street2": null, "fullAddress": "1239 Filbert St, Filadelfia, PA 19107", "locale": "pl"}, {"street1": null, "street2": null, "fullAddress": "1239 Filbert St, \u8d39\u57ce, PA", "locale": "zh_CN"}, {"street1": null, "street2": null, "fullAddress": "1239 Filbert St, Filadelfia, PA 19107", "locale": "es_CO"}, {"street1": null, "street2": null, "fullAddress": "1239 Filbert St, Philadelphie, PA 19107", "locale": "fr"}, {"street1": null, "street2": null, "fullAddress": "1239 Filbert St, \u30d5\u30a3\u30e9\u30c7\u30eb\u30d5\u30a3\u30a2, PA", "locale": "ja"}, {"street1": null, "street2": null, "fullAddress": "1239 Filbert St, \u05e4\u05d9\u05dc\u05d3\u05dc\u05e4\u05d9\u05d4, PA 19107", "locale": "iw"}, {"street1": null, "street2": null, "fullAddress": "1239 Filbert St, Philadelphia, PA 19107", "locale": "en_IN"}, {"street1": null, "street2": null, "fullAddress": "1239 Filbert St, Philadelphia, PA 19107", "locale": "de"}, {"street1": null, "street2": null, "fullAddress": "1239 Filbert St, \u8d39\u57ce, PA", "locale": "zh"}, {"street1": null, "street2": null, "fullAddress": "1239 Filbert St, Filadelfia, PA 19107", "locale": "es_PE"}, {"street1": null, "street2": null, "fullAddress": "1239 Filbert St, Philadelphia, PA 19107", "locale": "en_PH"}], "parents": [{"placeType": "CITY", "locationId": 60795, "name": "Philadelphia"}, {"placeType": "STATE", "locationId": 28959, "name": "Pennsylvania:"}, {"placeType": "COUNTRY", "locationId": 191, "name": "Hoa K\u1ef3"}, {"placeType": "CONTINENT", "locationId": 19, "name": "B\u0103\u0301c My\u0303"}, {"placeType": null, "locationId": 1, "name": "Th\u00ea\u0301 gi\u01a1\u0301i"}], "thumbnail": {"title": null, "photoSizes": [{"height": 0, "isHorizontal": false, "width": 0, "url": "https://dynamic-media-cdn.tripadvisor.com/media/photo-o/16/ed/55/d5/chili-s-grill-bar.jpg?w=100&h=100&s=1"}, {"height": 50, "isHorizontal": true, "width": 50, "url": "https://media-cdn.tripadvisor.com/media/photo-t/16/ed/55/d5/chili-s-grill-bar.jpg"}, {"height": 150, "isHorizontal": true, "width": 150, "url": "https://media-cdn.tripadvisor.com/media/photo-l/16/ed/55/d5/chili-s-grill-bar.jpg"}, {"height": 205, "isHorizontal": false, "width": 154, "url": "https://media-cdn.tripadvisor.com/media/photo-f/16/ed/55/d5/chili-s-grill-bar.jpg"}, {"height": 200, "isHorizontal": false, "width": 180, "url": "https://media-cdn.tripadvisor.com/media/photo-i/16/ed/55/d5/chili-s-grill-bar.jpg"}, {"height": 450, "isHorizontal": false, "width": 338, "url": "https://media-cdn.tripadvisor.com/media/photo-s/16/ed/55/d5/chili-s-grill-bar.jpg"}, {"height": 733, "isHorizontal": false, "width": 550, "url": "https://media-cdn.tripadvisor.com/media/photo-p/16/ed/55/d5/chili-s-grill-bar.jpg"}, {"height": 1280, "isHorizontal": false, "width": 960, "url": "https://media-cdn.tripadvisor.com/media/photo-m/1280/16/ed/55/d5/chili-s-grill-bar.jpg"}, {"height": 1365, "isHorizontal": false, "width": 1024, "url": "https://media-cdn.tripadvisor.com/media/photo-w/16/ed/55/d5/chili-s-grill-bar.jpg"}]}}]}}]